galvandi_sorting_magic2/__init__.py
galvandi_sorting_magic2/bubble_sort.py
galvandi_sorting_magic2/insertion_sort.py
galvandi_sorting_magic2/quick_sort.py
galvandi_sorting_magic2/selection_sort.py
galvandi_sorting_magic2-0.1.6.dist-info/METADATA
galvandi_sorting_magic2-0.1.6.dist-info/WHEEL
galvandi_sorting_magic2-0.1.6.dist-info/top_level.txt
galvandi_sorting_magic2-0.1.6.dist-info/RECORD
