Metadata-Version: 2.1
Name: galvandi-sorting-magic2
Version: 0.1.6
Summary: Just some magic
Home-page: http://github.com/galvandi
Author: galvandi
Author-email: galvandi@derp.com
License: MIT
Platform: UNKNOWN
